redis_extensions/__init__.py
redis_extensions/expires.py
redis_extensions/extensions.py
redis_extensions-4.1.5.dist-info/METADATA
redis_extensions-4.1.5.dist-info/WHEEL
redis_extensions-4.1.5.dist-info/top_level.txt
redis_extensions-4.1.5.dist-info/RECORD
