Metadata-Version: 2.1
Name: redis-extensions
Version: 4.1.5
Summary: Redis-extensions is a collection of custom extensions for Redis-py.
Home-page: https://github.com/RedisClub/redis-extensions-py/tree/redis4.x+py3.7+
Author: Hackathon
Author-email: kimi.huang@brightcells.com
License: UNKNOWN
Keywords: Redis Extensions
Platform: UNKNOWN
Classifier: License :: OSI Approved :: BSD License
Classifier: Programming Language :: Python
Classifier: Programming Language :: Python :: 3
Classifier: Programming Language :: Python :: 3.7
Classifier: Programming Language :: Python :: 3.8
Classifier: Programming Language :: Python :: 3.9
Classifier: Programming Language :: Python :: 3.10
Classifier: Topic :: Software Development :: Libraries :: Python Modules
Requires-Python: >=3.7
Requires-Dist: TimeConvert
Requires-Dist: redis (>=4.0.2)
Requires-Dist: shortuuid
Provides-Extra: advanced
Requires-Dist: verification-code ; extra == 'advanced'
Requires-Dist: graphic-verification-code (>=1.0.3) ; extra == 'advanced'
Provides-Extra: base
Provides-Extra: full
Requires-Dist: verification-code ; extra == 'full'
Requires-Dist: graphic-verification-code (>=1.0.3) ; extra == 'full'
Provides-Extra: gvcode
Requires-Dist: graphic-verification-code (>=1.0.3) ; extra == 'gvcode'
Provides-Extra: vcode
Requires-Dist: verification-code ; extra == 'vcode'
